snews_pt/__init__.py
snews_pt/__main__.py
snews_pt/_version.py
snews_pt/auxiliary/custom_script.py
snews_pt/auxiliary/detector_properties.json
snews_pt/auxiliary/firedrill_plugin.py
snews_pt/auxiliary/make_scenarios.py
snews_pt/auxiliary/scenarios.json
snews_pt/auxiliary/test-config.env
snews_pt/auxiliary/try_scenarios.py
snews_pt/core/__init__.py
snews_pt/core/logging.py
snews_pt/messages.py
snews_pt/remote_commands.py
snews_pt/snews_pt_utils.py
snews_pt/snews_sub.py
snews_pt/test/example_coincidence_tier_message.json
snews_pt/test/example_combined_message.json
snews_pt/test/example_heartbeat_message.json
snews_pt/test/example_significance_tier_message.json
snews_pt/test/example_timing_tier_message.json
snews_pt/test/generate_firedrill_json.py
snews_pt/test/random_plugin.py
snews_pt/test/test_install.py
snews_pt/test/test_messages.py
snews_pt/test/test_plugin.py
snews_pt-2.1.0.dist-info/AUTHORS
snews_pt-2.1.0.dist-info/LICENSE
snews_pt-2.1.0.dist-info/METADATA
snews_pt-2.1.0.dist-info/WHEEL
snews_pt-2.1.0.dist-info/entry_points.txt
snews_pt-2.1.0.dist-info/RECORD
