Metadata-Version: 2.3
Name: snews-pt
Version: 2.1.0
Summary: An alert application for observing supernovas
License: BSD-3-Clause
Author: SNEWS Collaboration
Author-email: snews2.0@lists.bnl.gov
Requires-Python: >=3.11,<4
Classifier: Programming Language :: Python
Classifier: Programming Language :: Python :: 3
Classifier: Intended Audience :: Science/Research
Classifier: Intended Audience :: Developers
Classifier: Natural Language :: English
Classifier: Topic :: Scientific/Engineering
Classifier: Topic :: Scientific/Engineering :: Astronomy
Classifier: Topic :: Scientific/Engineering :: Physics
Classifier: Operating System :: POSIX
Classifier: Operating System :: Unix
Classifier: Operating System :: MacOS
Classifier: License :: OSI Approved :: BSD License
Requires-Dist: click (>=8.1.7,<8.2.0)
Requires-Dist: hop-client (>=0.10.0,<0.11.0)
Requires-Dist: inquirer (>=2.8,<3.0)
Requires-Dist: numpy (>=1.26.3,<1.27.0)
Requires-Dist: python-dotenv (>=0.21.1,<0.22.0)
Requires-Dist: setuptools (>=66.1.0,<66.2.0)
Requires-Dist: snews-data-formats (>=1.0.0,<2.0.0)
Project-URL: Documentation, https://snews-publishing-tools.readthedocs.io
Project-URL: Homepage, https://snews2.org
Project-URL: Repository, https://github.com/SNEWS2/SNEWS_Publishing_Tools
